{"\\quad\\quad\\quad":{"\\quad\\quad\\quad":{"currentFile":{"count":40,"lastUpdated":1749363412616}}},"Continuity":{"Continuity":{"internalLink":{"count":25,"lastUpdated":1749339039076},"currentFile":{"count":2,"lastUpdated":1747811593825}}},"continuous":{"continuous":{"currentFile":{"count":70,"lastUpdated":1747811714397}}},"differentiable":{"differentiable":{"currentFile":{"count":27,"lastUpdated":1749342644548}}},"\\frac":{"\\frac":{"currentFile":{"count":22,"lastUpdated":1749372109314}}},"definition":{"definition":{"currentFile":{"count":5,"lastUpdated":1747247658215}}},"Metric Space":{"Metric Space":{"internalLink":{"count":5,"lastUpdated":1747245993209}}},"\\forall":{"\\forall":{"currentFile":{"count":6,"lastUpdated":1747795993471}}},"Derivative":{"Derivative":{"internalLink":{"count":5,"lastUpdated":1747809768593}}},"\\alpha":{"\\alpha":{"currentFile":{"count":126,"lastUpdated":1749338507879}}},"Supremum":{"Supremum":{"internalLink":{"count":4,"lastUpdated":1747245727790}}},"\\mathscr":{"\\mathscr":{"currentFile":{"count":25,"lastUpdated":1747246254655}}},"Riemann-Stieltjes Integral":{"Riemann-Stieltjes Integral":{"internalLink":{"count":6,"lastUpdated":1747811571384}}},"d\\alpha":{"d\\alpha":{"currentFile":{"count":11,"lastUpdated":1747249048004}}},"\\exists":{"\\exists":{"currentFile":{"count":4,"lastUpdated":1747792912613}}},"Proposition":{"Proposition":{"currentFile":{"count":6,"lastUpdated":1747792402293}}},"\\vepsi":{"\\vepsi":{"currentFile":{"count":10,"lastUpdated":1747811065370}}},"uniformly":{"uniformly":{"currentFile":{"count":19,"lastUpdated":1749341495469}}},"bounded":{"bounded":{"currentFile":{"count":4,"lastUpdated":1747788750191}}},"Sequences":{"Sequences":{"internalLink":{"count":3,"lastUpdated":1747249712475}}},"sequence":{"sequence":{"currentFile":{"count":5,"lastUpdated":1747791358896}}},"n\\to\\infty":{"n\\to\\infty":{"currentFile":{"count":2,"lastUpdated":1747248851067}}},"Definition":{"Definition":{"currentFile":{"count":5,"lastUpdated":1749364633407}}},"Example":{"Example":{"currentFile":{"count":2,"lastUpdated":1747250109481}}},"\\rrarrow":{"\\rrarrow":{"currentFile":{"count":5,"lastUpdated":1747796757607}}},"\\forall\\vepsi":{"\\forall\\vepsi":{"currentFile":{"count":1,"lastUpdated":1746905333710}}},"every":{"every":{"currentFile":{"count":1,"lastUpdated":1746905407801}}},"Criterion":{"Criterion":{"currentFile":{"count":2,"lastUpdated":1746906205869}}},"Crtier":{"Crtier":{"currentFile":{"count":1,"lastUpdated":1746906203887}}},"converges":{"converges":{"currentFile":{"count":5,"lastUpdated":1749361070780}}},"necessarily":{"necessarily":{"currentFile":{"count":3,"lastUpdated":1747250410698}}},"uniform":{"uniform":{"currentFile":{"count":1,"lastUpdated":1746907121064}}},"continuity":{"continuity":{"currentFile":{"count":2,"lastUpdated":1747811547568}}},"convergence":{"convergence":{"currentFile":{"count":7,"lastUpdated":1749360723935}}},"Cauchy Sequences":{"Cauchy Sequences":{"internalLink":{"count":2,"lastUpdated":1747248213060}}},"Continuous":{"Continuous":{"currentFile":{"count":2,"lastUpdated":1749343893012}}},"\\implies":{"\\implies":{"currentFile":{"count":1,"lastUpdated":1747245863590}}},"function":{"function":{"currentFile":{"count":2,"lastUpdated":1747249776369}}},"Uniformly":{"Uniformly":{"currentFile":{"count":2,"lastUpdated":1747249883309}}},"pointwise":{"pointwise":{"currentFile":{"count":4,"lastUpdated":1747795043370}}},"subsequence":{"subsequence":{"currentFile":{"count":7,"lastUpdated":1747847417754}}},"Bounded":{"Bounded":{"currentFile":{"count":1,"lastUpdated":1747260078440}}},"Equicontinuous":{"Equicontinuous":{"currentFile":{"count":2,"lastUpdated":1747796235233}}},"compact":{"compact":{"currentFile":{"count":1,"lastUpdated":1747791488735}}},"Compact Sets":{"Compact Sets":{"internalLink":{"count":2,"lastUpdated":1747792404805}}},"equicontinuous":{"equicontinuous":{"currentFile":{"count":3,"lastUpdated":1747847383864}}},"\\delta":{"\\delta":{"currentFile":{"count":1,"lastUpdated":1747792946760}}},"particular":{"particular":{"currentFile":{"count":2,"lastUpdated":1747795719526}}},"polynomial":{"polynomial":{"currentFile":{"count":2,"lastUpdated":1749362253979}}},"real-valued":{"real-valued":{"currentFile":{"count":1,"lastUpdated":1747796784712}}},"Uniform Convergence and Integration":{"Uniform Convergence and Integration":{"internalLink":{"count":1,"lastUpdated":1747809674714}}},"Pointwise and Uniform Convergence":{"Pointwise and Uniform Convergence":{"internalLink":{"count":1,"lastUpdated":1747809677638}}},"derivative":{"derivative":{"currentFile":{"count":2,"lastUpdated":1749340457192}}},"Differentiable":{"Differentiable":{"currentFile":{"count":4,"lastUpdated":1749343880859}}},"convergent":{"convergent":{"currentFile":{"count":3,"lastUpdated":1747847406739}}},"Bolzano-Weierstrass":{"Bolzano-Weierstrass":{"currentFile":{"count":1,"lastUpdated":1747813966266}}},"absolute":{"absolute":{"currentFile":{"count":1,"lastUpdated":1749339659835}}},"\\limsup":{"\\limsup":{"currentFile":{"count":2,"lastUpdated":1749340427296}}},"Differentiation":{"Differentiation":{"currentFile":{"count":1,"lastUpdated":1749341999427}}},"continuously":{"continuously":{"currentFile":{"count":1,"lastUpdated":1749359313958}}},"Power Series":{"Power Series":{"internalLink":{"count":1,"lastUpdated":1749361107797}}},"Taylor's Theorem":{"Taylor's Theorem":{"internalLink":{"count":1,"lastUpdated":1749361999747}}},"Trigonometric":{"Trigonometric":{"currentFile":{"count":1,"lastUpdated":1749362244092}}},"trigonometric":{"trigonometric":{"currentFile":{"count":2,"lastUpdated":1749369506293}}},"\\longleftrightarrow":{"\\longleftrightarrow":{"currentFile":{"count":2,"lastUpdated":1749363014454}}},"Orthonormal":{"Orthonormal":{"currentFile":{"count":1,"lastUpdated":1749364008623}}},"orthonormal":{"orthonormal":{"currentFile":{"count":4,"lastUpdated":1749369081089}}},"\\langle":{"\\langle":{"currentFile":{"count":6,"lastUpdated":1749366171646}}},"\\rangle":{"\\rangle":{"currentFile":{"count":5,"lastUpdated":1749364692021}}},"Product":{"Product":{"currentFile":{"count":1,"lastUpdated":1749364646891}}},"Fourier":{"Fourier":{"currentFile":{"count":1,"lastUpdated":1749369367363}}},"approximate":{"approximate":{"currentFile":{"count":3,"lastUpdated":1749369702482}}},"Trigonometric Functions":{"Trigonometric Functions":{"internalLink":{"count":1,"lastUpdated":1749369509961}}},"Approximations":{"Approximations":{"currentFile":{"count":1,"lastUpdated":1749371918514}}},"partial":{"partial":{"currentFile":{"count":1,"lastUpdated":1749372134894}}},"Series":{"Series":{"internalLink":{"count":1,"lastUpdated":1749373604886}}},"Coefficients":{"Coefficients":{"currentFile":{"count":2,"lastUpdated":1749374087882}}}}